skinport/__init__.py
skinport/client.py
skinport/color.py
skinport/enums.py
skinport/errors.py
skinport/http.py
skinport/item.py
skinport/iterators.py
skinport/sale.py
skinport/salefeed.py
skinport/skinport_msgpack_packet.py
skinport/transaction.py
skinport/utils.py
skinport_py-0.36.0.dist-info/licenses/LICENSE
skinport_py-0.36.0.dist-info/METADATA
skinport_py-0.36.0.dist-info/WHEEL
skinport_py-0.36.0.dist-info/top_level.txt
skinport_py-0.36.0.dist-info/RECORD
