Metadata-Version: 2.4
Name: skinport.py
Version: 0.36.0
Summary: A Python wrapper for the Skinport API
Author-email: PaxxPatriot <skinport.py@gmail.com>
License-Expression: MIT
Project-URL: Documentation, https://paxxpatriot.github.io/skinport.py/
Project-URL: Repository, https://github.com/PaxxPatriot/skinport.py.git
Project-URL: Issues, https://github.com/PaxxPatriot/skinport.py/issues
Keywords: Skinport,Counter-Strike 2,Team Fortress 2,Dota 2,Rust
Classifier: Development Status :: 3 - Alpha
Classifier: Environment :: Console
Classifier: Framework :: aiohttp
Classifier: Intended Audience :: Developers
Classifier: Natural Language :: English
Classifier: Operating System :: OS Independent
Classifier: Programming Language :: Python :: 3 :: Only
Classifier: Programming Language :: Python :: 3.11
Classifier: Programming Language :: Python :: 3.12
Classifier: Programming Language :: Python :: 3.13
Classifier: Programming Language :: Python :: 3.14
Classifier: Topic :: Internet
Classifier: Topic :: Software Development :: Libraries
Classifier: Topic :: Software Development :: Libraries :: Python Modules
Classifier: Topic :: Utilities
Classifier: Typing :: Typed
Requires-Python: >=3.11
License-File: LICENSE
Requires-Dist: aiohttp
Requires-Dist: asyncache
Requires-Dist: cachetools
Requires-Dist: python-socketio[asyncio_client]
Requires-Dist: msgpack
Requires-Dist: brotli>=1.2.0
Dynamic: license-file
